shelfdb/__init__.py
shelfdb/server.py
shelfdb/shelf.py
shelfdb/test_server.py
shelfdb/test_shelf.py
shelfdb-1.1.1.dist-info/LICENSE
shelfdb-1.1.1.dist-info/METADATA
shelfdb-1.1.1.dist-info/WHEEL
shelfdb-1.1.1.dist-info/entry_points.txt
shelfdb-1.1.1.dist-info/top_level.txt
shelfdb-1.1.1.dist-info/RECORD
