Metadata-Version: 2.1
Name: shelfdb
Version: 1.1.1
Summary: A tiny documents database for Python
Home-page: https://github.com/nitipit/shelfdb
Author: Nitipit Nontasuwan
Author-email: nitipit@gmail.com
Keywords: dict,json,database
Classifier: Programming Language :: Python :: 3.10
Classifier: License :: OSI Approved :: MIT License
Classifier: Operating System :: OS Independent
Requires-Python: >=3.10.0
License-File: LICENSE
Requires-Dist: dill (>=0.3.3)
Requires-Dist: uvloop (>=0.16.0) ; platform_system == "Linux"
